{"date": "2026-07-20", "mode": "csv", "ventes": {"ca_jour_ttc": 0.0, "ca_jour_ht": 0.0, "nb_ventes": 0, "ca_mois_ttc": 767000.0, "ca_annee_ttc": 767000.0, "panier_moyen": 0, "top_articles": [], "par_point_vente": []}, "tresorerie": {"caisse": 0.0, "banque": 0.0, "entrees_jour": 0.0, "sorties_jour": 0.0, "alerte": false}, "clients": {"impaye_total": 1044900.0, "nb_impayes": 4, "top_impayes": [{"client": "Colgate Togo", "montant": 590000.0, "echeance": "2026-07-21", "telephone": "+228 90234567", "email": "colgate.togo@eltys.tg", "facture": "F2026-002"}, {"client": "Commerce AMOUZOU", "montant": 331000.0, "echeance": "2026-08-06", "telephone": "+228 90678901", "email": "commerce.amouzou@eltys.tg", "facture": "F2026-006"}, {"client": "Quincaillerie GOE", "montant": 94400.0, "echeance": "2026-08-11", "telephone": "+228 90890123", "email": "quincaillerie.goe@eltys.tg", "facture": "F2026-008"}, {"client": "Menuiserie KOFFI", "montant": 29500.0, "echeance": "2026-07-26", "telephone": "+228 90456789", "email": "menuiserie.kofi@eltys.tg", "facture": "F2026-004"}], "concentration": 73.7}, "stock": {"valeur_stock": 23410000.0, "nb_references": 8, "stock_lent": [], "ruptures": []}, "alerts": [{"niveau": "orange", "titre": "Creances impayees", "detail": "4 factures impayees, total 1 044 900 FCFA."}, {"niveau": "orange", "titre": "Dependance clients", "detail": "73.7% du CA sur les 3 plus gros clients (risque de concentration)."}], "health_score": 84, "ai": {"resume": "La situation financière d'ELTYS SARLU est préoccupante avec une trésorerie nulle et des créances impayées s'élevant à 1 044 900 FCFA, représentant un risque significatif. De plus, la dépendance à trois clients majeurs pour 73,7% du chiffre d'affaires expose l'entreprise à des risques de concentration.", "recommandations": ["Mettre en place un plan de recouvrement des créances impayées pour réduire le montant de 1 044 900 FCFA.", "Diversifier la clientèle en ciblant de nouveaux clients pour diminuer la dépendance aux trois plus gros clients.", "Analyser et optimiser les marges sur les produits en ajustant les prix ou en réduisant les coûts d'approvisionnement.", "Évaluer la rotation des stocks et envisager des promotions pour réduire le stock de 23 410 000 FCFA.", "Établir un fonds de trésorerie pour faire face aux imprévus et éviter une situation de trésorerie nulle."], "veille": "Surveiller les tendances du marché local et les stratégies de prix de la concurrence, analyser les nouvelles offres de produits sur le marché togolais, et suivre les initiatives de fidélisation des clients mises en œuvre par d'autres distributeurs.", "ia_used": true}}